{
  "timestamp_utc": "2026-03-30T16:02:44Z",
  "discovery_sample": [
    {
      "symbol": "NOM",
      "score": 40.8,
      "vol": 96400538
    },
    {
      "symbol": "CFG",
      "score": 20.6,
      "vol": 36148080
    },
    {
      "symbol": "CHZ",
      "score": 18.2,
      "vol": 125203330
    },
    {
      "symbol": "TAO",
      "score": 11.7,
      "vol": 385418289
    },
    {
      "symbol": "FET",
      "score": 10.6,
      "vol": 118919445
    },
    {
      "symbol": "LDO",
      "score": 9.9,
      "vol": 37118426
    },
    {
      "symbol": "MON",
      "score": 7.5,
      "vol": 147691249
    },
    {
      "symbol": "RENDER",
      "score": 7.5,
      "vol": 58216982
    },
    {
      "symbol": "BTC",
      "score": 7.0,
      "vol": 37475387762
    },
    {
      "symbol": "ONDO",
      "score": 6.1,
      "vol": 65768208
    }
  ],
  "quick_suggestions": [
    {
      "action": "BUY_SMALL",
      "symbol": "NOM",
      "score": 40.8,
      "reason": "score 40.8, 24h +39.3%, 7d +38.4%",
      "tp_pct": 0.2,
      "sl_pct": 0.1,
      "origin": "discovery"
    }
  ]
}