{
  "timestamp_utc": "2025-11-28T14:17:07Z",
  "discovery_sample": [
    {
      "symbol": "TURBO",
      "score": 54.3,
      "vol": 372127005
    },
    {
      "symbol": "SQD",
      "score": 50.2,
      "vol": 105950203
    },
    {
      "symbol": "BAT",
      "score": 38.5,
      "vol": 163393949
    },
    {
      "symbol": "FARTCOIN",
      "score": 24.0,
      "vol": 147556992
    },
    {
      "symbol": "WLFI",
      "score": 18.4,
      "vol": 146108853
    },
    {
      "symbol": "1INCH",
      "score": 15.2,
      "vol": 68572531
    },
    {
      "symbol": "TRUST",
      "score": 15.0,
      "vol": 76084589
    },
    {
      "symbol": "BTC",
      "score": 10.1,
      "vol": 52916662495
    },
    {
      "symbol": "KITE",
      "score": 9.6,
      "vol": 70935393
    },
    {
      "symbol": "AAVE",
      "score": 7.1,
      "vol": 208517619
    }
  ],
  "quick_suggestions": [
    {
      "action": "BUY_SMALL",
      "symbol": "TURBO",
      "score": 54.3,
      "reason": "score 54.3, 24h +60.3%, 7d +93.5%",
      "tp_pct": 0.2,
      "sl_pct": 0.1,
      "origin": "discovery"
    },
    {
      "action": "BUY_SMALL",
      "symbol": "SQD",
      "score": 50.2,
      "reason": "score 50.2, 24h +50.8%, 7d +92.8%",
      "tp_pct": 0.2,
      "sl_pct": 0.1,
      "origin": "discovery"
    },
    {
      "action": "BUY_SMALL",
      "symbol": "BAT",
      "score": 38.5,
      "reason": "score 38.5, 24h +15.3%, 7d +65.8%",
      "tp_pct": 0.2,
      "sl_pct": 0.1,
      "origin": "discovery"
    }
  ]
}