{
  "timestamp_utc": "2025-12-23T15:18:03Z",
  "discovery_sample": [
    {
      "symbol": "AVNT",
      "score": 12.8,
      "vol": 131642826
    },
    {
      "symbol": "CHZ",
      "score": 9.0,
      "vol": 63810944
    },
    {
      "symbol": "BTC",
      "score": 7.0,
      "vol": 47198661333
    },
    {
      "symbol": "WET",
      "score": 5.8,
      "vol": 104207367
    },
    {
      "symbol": "ETH",
      "score": 3.3,
      "vol": 22520387996
    },
    {
      "symbol": "PAXG",
      "score": 3.2,
      "vol": 272347355
    },
    {
      "symbol": "BCH",
      "score": 1.8,
      "vol": 404941709
    },
    {
      "symbol": "SOL",
      "score": 0.5,
      "vol": 3699066914
    },
    {
      "symbol": "XRP",
      "score": 0.4,
      "vol": 2664406733
    },
    {
      "symbol": "BNB",
      "score": 0.1,
      "vol": 1053028156
    }
  ],
  "quick_suggestions": []
}