{
  "generated_at_utc": "2026-03-08T15:19:20+00:00",
  "universe": "top_200_coingecko_filtered",
  "projects": [
    {
      "symbol": "AAVE",
      "name": "Aave",
      "score": {
        "total": 16.0,
        "price_momentum": 0.0,
        "tvl_momentum": 0.0,
        "volume_momentum": 0.0041,
        "liquidity_quality": 0.0041,
        "holder_concentration": null
      },
      "metrics": {
        "price_usd": 106.8,
        "chg_24h": -0.030905763149770175,
        "chg_7d": -0.06552159902390883,
        "chg_30d": -0.02385410938739265,
        "volume_24h_usd": 201371115,
        "volume_chg_24h": null,
        "tvl_usd": 26481107221,
        "tvl_chg_7d": 0.005131313881868134,
        "tvl_chg_30d": -0.03945777493053723,
        "liq_cex_depth_2pct_usd": null,
        "liq_dex_pool_usd": null
      },
      "risk_flags": [],
      "sources": [
        "coingecko",
        "defillama"
      ]
    },
    {
      "symbol": "BTC",
      "name": "Bitcoin",
      "score": {
        "total": 4.4,
        "price_momentum": 0.0,
        "tvl_momentum": 0.0,
        "volume_momentum": 0.6327,
        "liquidity_quality": 0.6327,
        "holder_concentration": null
      },
      "metrics": {
        "price_usd": 67288,
        "chg_24h": -0.009972504717849627,
        "chg_7d": 0.00636554009524372,
        "chg_30d": -0.012130206188658975,
        "volume_24h_usd": 30728732508,
        "volume_chg_24h": null,
        "tvl_usd": 0.0,
        "tvl_chg_7d": 0.0,
        "tvl_chg_30d": 0.0,
        "liq_cex_depth_2pct_usd": null,
        "liq_dex_pool_usd": null
      },
      "risk_flags": [],
      "sources": [
        "coingecko"
      ]
    },
    {
      "symbol": "TRX",
      "name": "TRON",
      "score": {
        "total": 2.8,
        "price_momentum": 0.0465,
        "tvl_momentum": 0.0,
        "volume_momentum": 0.0083,
        "liquidity_quality": 0.0083,
        "holder_concentration": null
      },
      "metrics": {
        "price_usd": 0.288433,
        "chg_24h": 0.01314376350340516,
        "chg_7d": 0.02398819994856936,
        "chg_30d": 0.06528428371599299,
        "volume_24h_usd": 402735393,
        "volume_chg_24h": null,
        "tvl_usd": 0.0,
        "tvl_chg_7d": 0.0,
        "tvl_chg_30d": 0.0,
        "liq_cex_depth_2pct_usd": null,
        "liq_dex_pool_usd": null
      },
      "risk_flags": [],
      "sources": [
        "coingecko"
      ]
    },
    {
      "symbol": "UNI",
      "name": "Uniswap",
      "score": {
        "total": 2.3,
        "price_momentum": 0.0,
        "tvl_momentum": 0.0233,
        "volume_momentum": 0.0028,
        "liquidity_quality": 0.0028,
        "holder_concentration": null
      },
      "metrics": {
        "price_usd": 3.69,
        "chg_24h": -0.031200510550255873,
        "chg_7d": -0.031279714181567955,
        "chg_30d": 0.09213833090223195,
        "volume_24h_usd": 134122871,
        "volume_chg_24h": null,
        "tvl_usd": 3132108612,
        "tvl_chg_7d": 0.024354699758932532,
        "tvl_chg_30d": 0.022239538579997897,
        "liq_cex_depth_2pct_usd": null,
        "liq_dex_pool_usd": null
      },
      "risk_flags": [],
      "sources": [
        "coingecko",
        "defillama"
      ]
    },
    {
      "symbol": "ETH",
      "name": "Ethereum",
      "score": {
        "total": 1.9,
        "price_momentum": 0.0,
        "tvl_momentum": 0.0,
        "volume_momentum": 0.2745,
        "liquidity_quality": 0.2745,
        "holder_concentration": null
      },
      "metrics": {
        "price_usd": 1944.11,
        "chg_24h": -0.02103628438886115,
        "chg_7d": -0.0319583457683072,
        "chg_30d": -0.0019375835157299898,
        "volume_24h_usd": 13331402477,
        "volume_chg_24h": null,
        "tvl_usd": 0.0,
        "tvl_chg_7d": 0.0,
        "tvl_chg_30d": 0.0,
        "liq_cex_depth_2pct_usd": null,
        "liq_dex_pool_usd": null
      },
      "risk_flags": [],
      "sources": [
        "coingecko"
      ]
    }
  ],
  "diagnostics": {
    "params": {
      "min_score": 20.0,
      "min_volume_24h_usd": 10000000.0,
      "min_tvl_growth_7d": -0.02,
      "top_n": 5,
      "exclude_stables": true,
      "stables": [
        "DAI",
        "FDUSD",
        "TUSD",
        "USDC",
        "USDP",
        "USDT"
      ]
    },
    "counts": {
      "total_fetched": 25,
      "excluded_stables": 2,
      "below_min_volume": 2,
      "below_min_score": 21,
      "below_min_tvl_7d": 0,
      "passed_strong": 0,
      "top_returned": 5
    },
    "fallback_used": true,
    "returned_symbols": [
      [
        "AAVE",
        16.0
      ],
      [
        "BTC",
        4.4
      ],
      [
        "TRX",
        2.8
      ],
      [
        "UNI",
        2.3
      ],
      [
        "ETH",
        1.9
      ]
    ]
  },
  "discovery": {
    "discovery_sample": [
      {
        "symbol": "PLUME",
        "score": 38.7,
        "vol": 69157522
      },
      {
        "symbol": "KITE",
        "score": 21.7,
        "vol": 203783389
      },
      {
        "symbol": "AKT",
        "score": 13.6,
        "vol": 33669604
      },
      {
        "symbol": "ZRO",
        "score": 11.1,
        "vol": 82652532
      },
      {
        "symbol": "BTC",
        "score": 7.0,
        "vol": 30728732508
      },
      {
        "symbol": "CHZ",
        "score": 5.8,
        "vol": 48753969
      },
      {
        "symbol": "ALCX",
        "score": 5.1,
        "vol": 36306737
      },
      {
        "symbol": "TON",
        "score": 4.4,
        "vol": 72388342
      },
      {
        "symbol": "NEAR",
        "score": 4.2,
        "vol": 136281968
      },
      {
        "symbol": "ETH",
        "score": 3.0,
        "vol": 13331402477
      }
    ],
    "quick_suggestions": [
      {
        "action": "BUY_SMALL",
        "symbol": "PLUME",
        "score": 38.7,
        "reason": "score 38.7, 24h +22.1%, 7d +48.7%",
        "tp_pct": 0.2,
        "sl_pct": 0.1,
        "origin": "discovery"
      }
    ]
  }
}