{
  "generated_at_utc": "2026-04-19T15:34:23+00:00",
  "universe": "top_200_coingecko_filtered",
  "projects": [
    {
      "symbol": "AAVE",
      "name": "Aave",
      "score": {
        "total": 16.1,
        "price_momentum": 0.0,
        "tvl_momentum": 0.0,
        "volume_momentum": 0.0119,
        "liquidity_quality": 0.0119,
        "holder_concentration": null
      },
      "metrics": {
        "price_usd": 92.05,
        "chg_24h": -0.18540527314773964,
        "chg_7d": 0.026970980587408364,
        "chg_30d": -0.17005913086554045,
        "volume_24h_usd": 965838701,
        "volume_chg_24h": null,
        "tvl_usd": 19775358086,
        "tvl_chg_7d": -0.21589165759184983,
        "tvl_chg_30d": -0.21388076753413907,
        "liq_cex_depth_2pct_usd": null,
        "liq_dex_pool_usd": null
      },
      "risk_flags": [],
      "sources": [
        "coingecko",
        "defillama"
      ]
    },
    {
      "symbol": "ARB",
      "name": "Arbitrum",
      "score": {
        "total": 9.8,
        "price_momentum": 0.1637,
        "tvl_momentum": 0.0,
        "volume_momentum": 0.001,
        "liquidity_quality": 0.001,
        "holder_concentration": null
      },
      "metrics": {
        "price_usd": 0.127863,
        "chg_24h": -0.005038002415058746,
        "chg_7d": 0.14142472577303722,
        "chg_30d": 0.27940502280851026,
        "volume_24h_usd": 82018906,
        "volume_chg_24h": null,
        "tvl_usd": 0.0,
        "tvl_chg_7d": 0.0,
        "tvl_chg_30d": 0.0,
        "liq_cex_depth_2pct_usd": null,
        "liq_dex_pool_usd": null
      },
      "risk_flags": [],
      "sources": [
        "coingecko",
        "defillama"
      ]
    },
    {
      "symbol": "BTC",
      "name": "Bitcoin",
      "score": {
        "total": 8.9,
        "price_momentum": 0.0667,
        "tvl_momentum": 0.0,
        "volume_momentum": 0.7021,
        "liquidity_quality": 0.7021,
        "holder_concentration": null
      },
      "metrics": {
        "price_usd": 75885,
        "chg_24h": -0.004616690999979368,
        "chg_7d": 0.070139041514201,
        "chg_30d": 0.0861978243075072,
        "volume_24h_usd": 56976428206,
        "volume_chg_24h": null,
        "tvl_usd": 0.0,
        "tvl_chg_7d": 0.0,
        "tvl_chg_30d": 0.0,
        "liq_cex_depth_2pct_usd": null,
        "liq_dex_pool_usd": null
      },
      "risk_flags": [],
      "sources": [
        "coingecko"
      ]
    },
    {
      "symbol": "INJ",
      "name": "Injective",
      "score": {
        "total": 6.3,
        "price_momentum": 0.1054,
        "tvl_momentum": 0.0,
        "volume_momentum": 0.0005,
        "liquidity_quality": 0.0005,
        "holder_concentration": null
      },
      "metrics": {
        "price_usd": 3.28,
        "chg_24h": -0.003823134075308979,
        "chg_7d": 0.12964678929527773,
        "chg_30d": 0.06276015163897218,
        "volume_24h_usd": 43602578,
        "volume_chg_24h": null,
        "tvl_usd": 0.0,
        "tvl_chg_7d": 0.0,
        "tvl_chg_30d": 0.0,
        "liq_cex_depth_2pct_usd": null,
        "liq_dex_pool_usd": null
      },
      "risk_flags": [],
      "sources": [
        "coingecko"
      ]
    },
    {
      "symbol": "OP",
      "name": "Optimism",
      "score": {
        "total": 5.5,
        "price_momentum": 0.091,
        "tvl_momentum": 0.0,
        "volume_momentum": 0.0006,
        "liquidity_quality": 0.0006,
        "holder_concentration": null
      },
      "metrics": {
        "price_usd": 0.125044,
        "chg_24h": -0.02695777179220292,
        "chg_7d": 0.16029042175347213,
        "chg_30d": 0.008315622127156934,
        "volume_24h_usd": 49979976,
        "volume_chg_24h": null,
        "tvl_usd": 0.0,
        "tvl_chg_7d": 0.0,
        "tvl_chg_30d": 0.0,
        "liq_cex_depth_2pct_usd": null,
        "liq_dex_pool_usd": null
      },
      "risk_flags": [],
      "sources": [
        "coingecko",
        "defillama"
      ]
    }
  ],
  "diagnostics": {
    "params": {
      "min_score": 20.0,
      "min_volume_24h_usd": 10000000.0,
      "min_tvl_growth_7d": -0.02,
      "top_n": 5,
      "exclude_stables": true,
      "stables": [
        "DAI",
        "FDUSD",
        "TUSD",
        "USDC",
        "USDP",
        "USDT"
      ]
    },
    "counts": {
      "total_fetched": 25,
      "excluded_stables": 2,
      "below_min_volume": 2,
      "below_min_score": 21,
      "below_min_tvl_7d": 0,
      "passed_strong": 0,
      "top_returned": 5
    },
    "fallback_used": true,
    "returned_symbols": [
      [
        "AAVE",
        16.1
      ],
      [
        "ARB",
        9.8
      ],
      [
        "BTC",
        8.9
      ],
      [
        "INJ",
        6.3
      ],
      [
        "OP",
        5.5
      ]
    ]
  },
  "discovery": {
    "discovery_sample": [
      {
        "symbol": "BLUR",
        "score": 48.9,
        "vol": 209792454
      },
      {
        "symbol": "ENJ",
        "score": 41.7,
        "vol": 246032413
      },
      {
        "symbol": "BIO",
        "score": 34.5,
        "vol": 150810458
      },
      {
        "symbol": "GTC",
        "score": 32.6,
        "vol": 65346597
      },
      {
        "symbol": "CFG",
        "score": 30.3,
        "vol": 48721196
      },
      {
        "symbol": "ARKM",
        "score": 21.8,
        "vol": 99188781
      },
      {
        "symbol": "HIGH",
        "score": 15.3,
        "vol": 384160845
      },
      {
        "symbol": "TIA",
        "score": 15.1,
        "vol": 49798783
      },
      {
        "symbol": "MOVE",
        "score": 14.4,
        "vol": 252881791
      },
      {
        "symbol": "ENA",
        "score": 13.9,
        "vol": 126565114
      }
    ],
    "quick_suggestions": [
      {
        "action": "BUY_SMALL",
        "symbol": "BLUR",
        "score": 48.9,
        "reason": "score 48.9, 24h +32.8%, 7d +49.0%",
        "tp_pct": 0.2,
        "sl_pct": 0.1,
        "origin": "discovery"
      },
      {
        "action": "BUY_SMALL",
        "symbol": "ENJ",
        "score": 41.7,
        "reason": "score 41.7, 24h +20.5%, 7d +50.2%",
        "tp_pct": 0.2,
        "sl_pct": 0.1,
        "origin": "discovery"
      },
      {
        "action": "BUY_SMALL",
        "symbol": "BIO",
        "score": 34.5,
        "reason": "score 34.5, 24h +9.0%, 7d +68.0%",
        "tp_pct": 0.2,
        "sl_pct": 0.1,
        "origin": "discovery"
      },
      {
        "action": "BUY_SMALL",
        "symbol": "GTC",
        "score": 32.6,
        "reason": "score 32.6, 24h +11.8%, 7d +46.7%",
        "tp_pct": 0.2,
        "sl_pct": 0.1,
        "origin": "discovery"
      },
      {
        "action": "BUY_SMALL",
        "symbol": "CFG",
        "score": 30.3,
        "reason": "score 30.3, 24h +12.5%, 7d +35.4%",
        "tp_pct": 0.2,
        "sl_pct": 0.1,
        "origin": "discovery"
      }
    ]
  }
}