{
  "generated_at_utc": "2026-04-14T16:04:21+00:00",
  "universe": "top_200_coingecko_filtered",
  "projects": [
    {
      "symbol": "AAVE",
      "name": "Aave",
      "score": {
        "total": 24.7,
        "price_momentum": 0.1389,
        "tvl_momentum": 0.0214,
        "volume_momentum": 0.0032,
        "liquidity_quality": 0.0032,
        "holder_concentration": null
      },
      "metrics": {
        "price_usd": 99.8,
        "chg_24h": 0.05994013851951622,
        "chg_7d": 0.14295787714620445,
        "chg_30d": -0.1165355380218161,
        "volume_24h_usd": 338505342,
        "volume_chg_24h": null,
        "tvl_usd": 26161551433,
        "tvl_chg_7d": 0.03475989839934522,
        "tvl_chg_30d": 0.008005679299545864,
        "liq_cex_depth_2pct_usd": null,
        "liq_dex_pool_usd": null
      },
      "risk_flags": [],
      "sources": [
        "coingecko",
        "defillama"
      ]
    }
  ],
  "diagnostics": {
    "params": {
      "min_score": 20.0,
      "min_volume_24h_usd": 10000000.0,
      "min_tvl_growth_7d": -0.02,
      "top_n": 5,
      "exclude_stables": true,
      "stables": [
        "DAI",
        "FDUSD",
        "TUSD",
        "USDC",
        "USDP",
        "USDT"
      ]
    },
    "counts": {
      "total_fetched": 25,
      "excluded_stables": 2,
      "below_min_volume": 1,
      "below_min_score": 21,
      "below_min_tvl_7d": 0,
      "passed_strong": 1,
      "top_returned": 1
    },
    "fallback_used": false,
    "returned_symbols": [
      [
        "AAVE",
        24.7
      ]
    ]
  },
  "discovery": {
    "discovery_sample": [
      {
        "symbol": "RAVE",
        "score": 60.1,
        "vol": 682394634
      },
      {
        "symbol": "ENJ",
        "score": 53.4,
        "vol": 358972709
      },
      {
        "symbol": "ZAMA",
        "score": 50.0,
        "vol": 229159055
      },
      {
        "symbol": "MON",
        "score": 27.1,
        "vol": 123861652
      },
      {
        "symbol": "WET",
        "score": 26.9,
        "vol": 111479719
      },
      {
        "symbol": "ZEC",
        "score": 25.8,
        "vol": 533589615
      },
      {
        "symbol": "FARTCOIN",
        "score": 24.8,
        "vol": 58223788
      },
      {
        "symbol": "PLUME",
        "score": 22.5,
        "vol": 70465698
      },
      {
        "symbol": "LDO",
        "score": 18.4,
        "vol": 101718377
      },
      {
        "symbol": "ETH",
        "score": 16.0,
        "vol": 31207379612
      }
    ],
    "quick_suggestions": [
      {
        "action": "BUY_SMALL",
        "symbol": "RAVE",
        "score": 60.1,
        "reason": "score 60.1, 24h +65.4%, 7d +6189.7%",
        "tp_pct": 0.2,
        "sl_pct": 0.1,
        "origin": "discovery"
      },
      {
        "action": "BUY_SMALL",
        "symbol": "ENJ",
        "score": 53.4,
        "reason": "score 53.4, 24h +39.4%, 7d +220.8%",
        "tp_pct": 0.2,
        "sl_pct": 0.1,
        "origin": "discovery"
      },
      {
        "action": "BUY_SMALL",
        "symbol": "ZAMA",
        "score": 50.0,
        "reason": "score 50.0, 24h +33.9%, 7d +60.0%",
        "tp_pct": 0.2,
        "sl_pct": 0.1,
        "origin": "discovery"
      },
      {
        "action": "BUY_SMALL",
        "symbol": "MON",
        "score": 27.1,
        "reason": "score 27.1, 24h +6.8%, 7d +36.1%",
        "tp_pct": 0.2,
        "sl_pct": 0.1,
        "origin": "discovery"
      },
      {
        "action": "BUY_SMALL",
        "symbol": "WET",
        "score": 26.9,
        "reason": "score 26.9, 24h +4.6%, 7d +42.7%",
        "tp_pct": 0.2,
        "sl_pct": 0.1,
        "origin": "discovery"
      },
      {
        "action": "BUY_SMALL",
        "symbol": "ZEC",
        "score": 25.8,
        "reason": "score 25.8, 24h +4.2%, 7d +36.7%",
        "tp_pct": 0.2,
        "sl_pct": 0.1,
        "origin": "discovery"
      }
    ]
  }
}