{
  "generated_at_utc": "2025-11-18T14:16:01+00:00",
  "universe": "top_200_coingecko_filtered",
  "projects": [],
  "diagnostics": {
    "params": {
      "min_score": 20.0,
      "min_volume_24h_usd": 10000000.0,
      "min_tvl_growth_7d": -0.02,
      "top_n": 5,
      "exclude_stables": true,
      "stables": [
        "DAI",
        "FDUSD",
        "TUSD",
        "USDC",
        "USDP",
        "USDT"
      ]
    },
    "counts": {
      "total_fetched": 0,
      "excluded_stables": 0,
      "below_min_volume": 0,
      "below_min_score": 0,
      "below_min_tvl_7d": 0,
      "passed_strong": 0,
      "top_returned": 0
    },
    "fallback_used": true,
    "returned_symbols": []
  },
  "discovery": {
    "discovery_sample": [],
    "quick_suggestions": []
  }
}