{
  "generated_at_utc": "2026-04-22T15:08:50+00:00",
  "universe": "top_200_coingecko_filtered",
  "projects": [
    {
      "symbol": "AAVE",
      "name": "Aave",
      "score": {
        "total": 16.0,
        "price_momentum": 0.0,
        "tvl_momentum": 0.0,
        "volume_momentum": 0.0044,
        "liquidity_quality": 0.0044,
        "holder_concentration": null
      },
      "metrics": {
        "price_usd": 93.99,
        "chg_24h": 0.02435837742699274,
        "chg_7d": -0.08841773502818139,
        "chg_30d": -0.14933348258706416,
        "volume_24h_usd": 354895026,
        "volume_chg_24h": null,
        "tvl_usd": 15849041209,
        "tvl_chg_7d": -0.39926701747950394,
        "tvl_chg_30d": -0.3776176327093464,
        "liq_cex_depth_2pct_usd": null,
        "liq_dex_pool_usd": null
      },
      "risk_flags": [],
      "sources": [
        "coingecko",
        "defillama"
      ]
    },
    {
      "symbol": "BTC",
      "name": "Bitcoin",
      "score": {
        "total": 11.3,
        "price_momentum": 0.1162,
        "tvl_momentum": 0.0,
        "volume_momentum": 0.6172,
        "liquidity_quality": 0.6172,
        "holder_concentration": null
      },
      "metrics": {
        "price_usd": 78951,
        "chg_24h": 0.04268181923563765,
        "chg_7d": 0.0646768789230285,
        "chg_30d": 0.10554780699030325,
        "volume_24h_usd": 49242576994,
        "volume_chg_24h": null,
        "tvl_usd": 0.0,
        "tvl_chg_7d": 0.0,
        "tvl_chg_30d": 0.0,
        "liq_cex_depth_2pct_usd": null,
        "liq_dex_pool_usd": null
      },
      "risk_flags": [],
      "sources": [
        "coingecko"
      ]
    },
    {
      "symbol": "ARB",
      "name": "Arbitrum",
      "score": {
        "total": 10.3,
        "price_momentum": 0.1712,
        "tvl_momentum": 0.0,
        "volume_momentum": 0.001,
        "liquidity_quality": 0.001,
        "holder_concentration": null
      },
      "metrics": {
        "price_usd": 0.12765,
        "chg_24h": 0.0026999488446595617,
        "chg_7d": 0.12477176425190213,
        "chg_30d": 0.3289415535734283,
        "volume_24h_usd": 76341058,
        "volume_chg_24h": null,
        "tvl_usd": 0.0,
        "tvl_chg_7d": 0.0,
        "tvl_chg_30d": 0.0,
        "liq_cex_depth_2pct_usd": null,
        "liq_dex_pool_usd": null
      },
      "risk_flags": [],
      "sources": [
        "coingecko",
        "defillama"
      ]
    },
    {
      "symbol": "UNI",
      "name": "Uniswap",
      "score": {
        "total": 9.6,
        "price_momentum": 0.0922,
        "tvl_momentum": 0.0342,
        "volume_momentum": 0.0021,
        "liquidity_quality": 0.0021,
        "holder_concentration": null
      },
      "metrics": {
        "price_usd": 3.41,
        "chg_24h": 0.050527171930326166,
        "chg_7d": 0.0714358012120537,
        "chg_30d": -0.05181618827899192,
        "volume_24h_usd": 168862818,
        "volume_chg_24h": null,
        "tvl_usd": 3388346105,
        "tvl_chg_7d": 0.02345003787486862,
        "tvl_chg_30d": 0.044984365733259875,
        "liq_cex_depth_2pct_usd": null,
        "liq_dex_pool_usd": null
      },
      "risk_flags": [],
      "sources": [
        "coingecko",
        "defillama"
      ]
    },
    {
      "symbol": "IMX",
      "name": "Immutable",
      "score": {
        "total": 8.1,
        "price_momentum": 0.1355,
        "tvl_momentum": 0.0,
        "volume_momentum": 0.0002,
        "liquidity_quality": 0.0002,
        "holder_concentration": null
      },
      "metrics": {
        "price_usd": 0.176361,
        "chg_24h": -0.00016411934799502565,
        "chg_7d": 0.14928534573466326,
        "chg_30d": 0.11382137028815331,
        "volume_24h_usd": 16127525,
        "volume_chg_24h": null,
        "tvl_usd": 0.0,
        "tvl_chg_7d": 0.0,
        "tvl_chg_30d": 0.0,
        "liq_cex_depth_2pct_usd": null,
        "liq_dex_pool_usd": null
      },
      "risk_flags": [],
      "sources": [
        "coingecko"
      ]
    }
  ],
  "diagnostics": {
    "params": {
      "min_score": 20.0,
      "min_volume_24h_usd": 10000000.0,
      "min_tvl_growth_7d": -0.02,
      "top_n": 5,
      "exclude_stables": true,
      "stables": [
        "DAI",
        "FDUSD",
        "TUSD",
        "USDC",
        "USDP",
        "USDT"
      ]
    },
    "counts": {
      "total_fetched": 25,
      "excluded_stables": 2,
      "below_min_volume": 1,
      "below_min_score": 22,
      "below_min_tvl_7d": 0,
      "passed_strong": 0,
      "top_returned": 5
    },
    "fallback_used": true,
    "returned_symbols": [
      [
        "AAVE",
        16.0
      ],
      [
        "BTC",
        11.3
      ],
      [
        "ARB",
        10.3
      ],
      [
        "UNI",
        9.6
      ],
      [
        "IMX",
        8.1
      ]
    ]
  },
  "discovery": {
    "discovery_sample": [
      {
        "symbol": "SPK",
        "score": 49.4,
        "vol": 97023234
      },
      {
        "symbol": "MET",
        "score": 35.9,
        "vol": 253160140
      },
      {
        "symbol": "CHIP",
        "score": 31.3,
        "vol": 1444315880
      },
      {
        "symbol": "OPG",
        "score": 31.1,
        "vol": 146266308
      },
      {
        "symbol": "HIGH",
        "score": 24.1,
        "vol": 76050021
      },
      {
        "symbol": "PENGU",
        "score": 20.8,
        "vol": 225075077
      },
      {
        "symbol": "STRK",
        "score": 17.3,
        "vol": 57390993
      },
      {
        "symbol": "AVNT",
        "score": 15.5,
        "vol": 66950498
      },
      {
        "symbol": "FLOKI",
        "score": 14.1,
        "vol": 48396908
      },
      {
        "symbol": "BTC",
        "score": 14.0,
        "vol": 49245356785
      }
    ],
    "quick_suggestions": [
      {
        "action": "BUY_SMALL",
        "symbol": "SPK",
        "score": 49.4,
        "reason": "score 49.4, 24h +32.9%, 7d +60.6%",
        "tp_pct": 0.2,
        "sl_pct": 0.1,
        "origin": "discovery"
      },
      {
        "action": "BUY_SMALL",
        "symbol": "MET",
        "score": 35.9,
        "reason": "score 35.9, 24h +25.6%, 7d +35.8%",
        "tp_pct": 0.2,
        "sl_pct": 0.1,
        "origin": "discovery"
      },
      {
        "action": "BUY_SMALL",
        "symbol": "CHIP",
        "score": 31.3,
        "reason": "score 31.3, 24h +83.9%, 7d +0.0%",
        "tp_pct": 0.2,
        "sl_pct": 0.1,
        "origin": "discovery"
      },
      {
        "action": "BUY_SMALL",
        "symbol": "OPG",
        "score": 31.1,
        "reason": "score 31.1, 24h +95.9%, 7d +0.0%",
        "tp_pct": 0.2,
        "sl_pct": 0.1,
        "origin": "discovery"
      }
    ]
  }
}